twelvefactor.py
twelvefactor-0.1.2.dist-info/DESCRIPTION.rst
twelvefactor-0.1.2.dist-info/METADATA
twelvefactor-0.1.2.dist-info/RECORD
twelvefactor-0.1.2.dist-info/WHEEL
twelvefactor-0.1.2.dist-info/metadata.json
twelvefactor-0.1.2.dist-info/top_level.txt
